proteosushi/__init__.py
proteosushi/__main__.py
proteosushi/combine_intensities.py
proteosushi/combine_output_annotations.py
proteosushi/download_uniprot_AS.py
proteosushi/parse_MaxQuant.py
proteosushi/parse_generic.py
proteosushi/parse_mascot.py
proteosushi/parse_proteome.py
proteosushi/proteoSushi_constants.py
proteosushi/proteosushi_gui.py
proteosushi/ps_digest.py
proteosushi/ps_utilities.py
proteosushi/run_proteoSushi.py
proteosushi/sparql.py
proteosushi/spec_list_fixed.tsv
proteosushi/test_annot_score_download.py
proteosushi/test_sparql.py
proteosushi/lib/__init__.py
proteosushi/lib/spec_list_fixed.tsv
proteosushi-1.7.0.dist-info/licenses/LICENSE
proteosushi-1.7.0.dist-info/METADATA
proteosushi-1.7.0.dist-info/WHEEL
proteosushi-1.7.0.dist-info/top_level.txt
proteosushi-1.7.0.dist-info/RECORD
