Metadata-Version: 2.4
Name: proteosushi
Version: 1.7.0
Summary: A bioinformatics tool for proteomics data analysis
Home-page: https://github.com/HeldLab/ProteoSushi
Download-URL: https://github.com/HeldLab/ProteoSushi/archive/v1.7.0.tar.gz
Author: Rob Seymour
Author-email: Rob Seymour <r27seymour@gmail.com>
License: GPL-3.0
Project-URL: Homepage, https://github.com/HeldLab/ProteoSushi
Project-URL: Download, https://github.com/HeldLab/ProteoSushi/archive/v1.7.0.tar.gz
Classifier: Development Status :: 5 - Production/Stable
Classifier: Environment :: X11 Applications :: Qt
Classifier: Intended Audience :: Science/Research
Classifier: Programming Language :: Python :: 3
Classifier: Natural Language :: English
Classifier: Operating System :: MacOS
Classifier: Operating System :: Microsoft :: Windows
Classifier: Operating System :: POSIX :: Linux
Classifier: Topic :: Scientific/Engineering :: Bio-Informatics
Requires-Python: >=3.7
License-File: LICENSE
Requires-Dist: PyQt5>=5.15
Requires-Dist: requests>=2.24
Requires-Dist: pandas>=1.0
Dynamic: author
Dynamic: download-url
Dynamic: home-page
Dynamic: license-file
Dynamic: requires-python
